hanabi_learning_environment/pyhanabi.h
hanabi_learning_environment/pyhanabi.py
hanabi_learning_environment/rl_env.py
hanabi_learning_environment/__init__.py
hanabi_learning_environment/libpyhanabi.so
hanabi_learning_environment/agents/random_agent.py
hanabi_learning_environment/agents/__init__.py
hanabi_learning_environment/agents/simple_agent.py
ws2223_group7_hanabi_learning_environment-0.0.3.dist-info/top_level.txt
ws2223_group7_hanabi_learning_environment-0.0.3.dist-info/METADATA
ws2223_group7_hanabi_learning_environment-0.0.3.dist-info/LICENSE
ws2223_group7_hanabi_learning_environment-0.0.3.dist-info/RECORD
ws2223_group7_hanabi_learning_environment-0.0.3.dist-info/WHEEL
