Metadata-Version: 2.1
Name: ws2223-group7-hanabi-learning-environment
Version: 0.0.3
Summary: ws2223-group7 Learning environment for the game of hanabi.
Author: ws2223-group7/hanabi-learning-environment
Classifier: Programming Language :: Python :: 3
Classifier: Operating System :: POSIX :: Linux
Requires-Python: >=3.6
License-File: LICENSE
Requires-Dist: cffi
